uxtime/MANIFEST.in
uxtime/__init__.py
uxtime/__main__.py
uxtime/unixtimec.py
uxtime/uxconverter.png
uxtime/docs/LICENSE.md
uxtime/docs/README.md
uxtime/docs/changes.rst
uxtime/docs/help.html
uxtime/docs/license.html
uxtime/res/__init__.py
uxtime/res/constants.py
uxtime/res/mainapp.py
uxtime/res/tools.py
uxtime/res/ux_logo_white_16.png
uxtime/res/ux_logo_white_32.png
uxtime/res/ux_logo_white_64.png
uxtime/res/views.py
uxtime/tests/__init__.py
uxtime/tests/test_time.py
uxtime-1.1.0.dist-info/licenses/LICENSE.md
uxtime-1.1.0.dist-info/METADATA
uxtime-1.1.0.dist-info/WHEEL
uxtime-1.1.0.dist-info/entry_points.txt
uxtime-1.1.0.dist-info/top_level.txt
uxtime-1.1.0.dist-info/RECORD
